indieauth.py
indieauth-0.1.1.dist-info/METADATA
indieauth-0.1.1.dist-info/entry_points.txt
indieauth-0.1.1.dist-info/WHEEL
indieauth-0.1.1.dist-info/RECORD
