Metadata-Version: 2.1
Name: indieauth
Version: 0.1.1
Summary: utilities for implementing IndieAuth clients and servers
License: 0BSD
Keywords: IndieWeb,IndieAuth
Author: Angelo Gladding
Author-email: angelo@ragt.ag
Requires-Python: >=3.10,<3.11
Classifier: License :: Other/Proprietary License
Classifier: Programming Language :: Python :: 3
Classifier: Programming Language :: Python :: 3.10
Requires-Dist: pycryptodome (>=3.16.0,<4.0.0)
Requires-Dist: txtint (>=0.0)
Requires-Dist: webagt (>=0.0)
